style_ranker/__init__.py
style_ranker/consts.py
style_ranker/dedup.py
style_ranker/rank.py
style_ranker/utils.py
style_ranker/llm/__init__.py
style_ranker/llm/train.py
style_ranker/ranker/__init__.py
style_ranker/ranker/config.py
style_ranker/ranker/data_synthesize.py
style_ranker/ranker/dataset.py
style_ranker/ranker/model.py
style_ranker/ranker/quality_measure.py
style_ranker/ranker/train.py
scar_tool-0.35.dist-info/METADATA
scar_tool-0.35.dist-info/WHEEL
scar_tool-0.35.dist-info/top_level.txt
scar_tool-0.35.dist-info/RECORD
