Metadata-Version: 2.1
Name: scar-tool
Version: 0.35
Summary: SCAR: An AI-powered tool for ranking and filtering instruction-answer pairs based on writing quality and style consistency
Home-page: https://github.com/zhuang-li/SCAR
Author: Zhuang Li
Author-email: zhuang.li1@monash.edu
Classifier: Programming Language :: Python :: 3
Classifier: License :: OSI Approved :: MIT License
Classifier: Operating System :: OS Independent
Requires-Dist: torch >=2.3
Requires-Dist: transformers >=4.37
Requires-Dist: huggingface-hub >=0.23
Requires-Dist: scikit-learn
Requires-Dist: tqdm
Requires-Dist: nltk
Requires-Dist: datasketch
